pygraph/__init__.py
pygraph/cli.py
pygraph_cli-0.1.0.dist-info/DESCRIPTION.rst
pygraph_cli-0.1.0.dist-info/METADATA
pygraph_cli-0.1.0.dist-info/RECORD
pygraph_cli-0.1.0.dist-info/WHEEL
pygraph_cli-0.1.0.dist-info/entry_points.txt
pygraph_cli-0.1.0.dist-info/metadata.json
pygraph_cli-0.1.0.dist-info/top_level.txt
