Metadata-Version: 2.0
Name: pygraph-cli
Version: 0.1.0
Summary: CLI for pygraphviz powered by graphviz
Home-page: https://github.com/EntilZha/pygraph
Author: Pedro Rodriguez
Author-email: ski.rodriguez@gmail.com
License: MIT
Keywords: graph visualization graphviz python cli
Platform: UNKNOWN
Classifier: Development Status :: 4 - Beta
Classifier: Intended Audience :: Developers
Classifier: License :: OSI Approved :: MIT License
Classifier: Programming Language :: Python :: 2.7
Classifier: Programming Language :: Python :: Implementation :: CPython
Classifier: Natural Language :: English
Classifier: Operating System :: OS Independent
Classifier: Topic :: Software Development :: Libraries :: Python Modules
Requires-Dist: click
Requires-Dist: graphviz
Requires-Dist: pyfunctional
